pyuvis/__init__.py
pyuvis/_nbdev.py
pyuvis/archive.py
pyuvis/calib.py
pyuvis/downloads.py
pyuvis/hsp_sensitivity.py
pyuvis/idlsav.py
pyuvis/io.py
pyuvis-0.5.0.dist-info/LICENSE
pyuvis-0.5.0.dist-info/METADATA
pyuvis-0.5.0.dist-info/WHEEL
pyuvis-0.5.0.dist-info/entry_points.txt
pyuvis-0.5.0.dist-info/top_level.txt
pyuvis-0.5.0.dist-info/RECORD
