Metadata-Version: 2.1
Name: pyuvis
Version: 0.5.0
Summary: Python tools for Cassini UVIS data
Home-page: https://github.com/michaelaye/pyuvis/tree/master/
Author: Michael Aye
Author-email: kmichael.aye@gmail.com
License: Apache Software License 2.0
Keywords: Cassini UVIS Data Tools
Platform: UNKNOWN
Classifier: Development Status :: 3 - Alpha
Classifier: Intended Audience :: Developers
Classifier: License :: OSI Approved :: Apache Software License
Classifier: Natural Language :: English
Classifier: Programming Language :: Python :: 3.7
Classifier: Programming Language :: Python :: 3.8
Requires-Python: >=3.7
License-File: LICENSE
Requires-Dist: pip
Requires-Dist: packaging
Requires-Dist: pandas
Requires-Dist: xarray
Requires-Dist: planetarypy (>=0.12)
Provides-Extra: dev
